main.py
ospylib-0.0.2.dist-info/METADATA
ospylib-0.0.2.dist-info/WHEEL
ospylib-0.0.2.dist-info/top_level.txt
ospylib-0.0.2.dist-info/RECORD
